slapstack/__init__.py
slapstack/core.py
slapstack/core_events.py
slapstack/core_logger.py
slapstack/core_state.py
slapstack/core_state_agv_manager.py
slapstack/core_state_lane_manager.py
slapstack/core_state_location_manager.py
slapstack/core_state_route_manager.py
slapstack/core_state_zone_manager.py
slapstack/helpers.py
slapstack/interface.py
slapstack/interface_input.py
slapstack/interface_templates.py
slapstack/use_cases/crossstacks/1_layout.csv
slapstack/use_cases/crossstacks/2_orders.json
slapstack/use_cases/crossstacks/3_initial_fill_lvl.json
slapstack/use_cases/wepastacks/1_layout.csv
slapstack/use_cases/wepastacks/2_orders.json
slapstack/use_cases/wepastacks/3_initial_fill_lvl.json
slapstack-0.1.1.dist-info/LICENSE
slapstack-0.1.1.dist-info/METADATA
slapstack-0.1.1.dist-info/WHEEL
slapstack-0.1.1.dist-info/top_level.txt
slapstack-0.1.1.dist-info/RECORD
