Metadata-Version: 2.1
Name: slapstack
Version: 0.1.1
Summary: An Event Discrete Simulation Framework for Block-Stacking Warehouses.
Home-page: UNKNOWN
License: UNKNOWN
Platform: UNKNOWN
Requires-Python: >3.6.8
License-File: LICENSE
Requires-Dist: gym
Requires-Dist: numpy
Requires-Dist: joblib
Requires-Dist: pandas
Requires-Dist: scipy
